data_processing_library/__init__.py
data_processing_library/async_group.py
data_processing_library/async_processor.py
data_processing_library/context.py
data_processing_library/group.py
data_processing_library/processor.py
data_processing_library-0.1.1.dist-info/LICENSE
data_processing_library-0.1.1.dist-info/WHEEL
data_processing_library-0.1.1.dist-info/METADATA
data_processing_library-0.1.1.dist-info/RECORD
